LICENSE
MANIFEST.in
README.md
requirements.txt
setup.py
bandcampscrape/__init__.py
bandcampscrape/bandcampscrape.py
bandcampscrape.egg-info/PKG-INFO
bandcampscrape.egg-info/SOURCES.txt
bandcampscrape.egg-info/dependency_links.txt
bandcampscrape.egg-info/entry_points.txt
bandcampscrape.egg-info/requires.txt
bandcampscrape.egg-info/top_level.txt