Metadata-Version: 1.1
Name: bandcampscrape
Version: 0.0.2
Summary: Downloader for BandCamp albums 
Home-page: https://github.com/ronier/bandcampscrape
Author: Ronier Lopez
Author-email: ronier@gmail.com
License: MIT License
Platform: UNKNOWN
Classifier: Environment :: Console
Classifier: License :: OSI Approved :: Apache Software License
Classifier: Operating System :: OS Independent
Classifier: Programming Language :: Python
Classifier: Programming Language :: Python :: 2.6
Classifier: Programming Language :: Python :: 2.7
Classifier: Topic :: Internet :: WWW/HTTP
Classifier: Topic :: Internet :: WWW/HTTP :: Dynamic Content
